astrality/__init__.py
astrality/actions.py
astrality/astrality.py
astrality/compiler.py
astrality/config.py
astrality/context.py
astrality/event_listener.py
astrality/exceptions.py
astrality/filewatcher.py
astrality/github.py
astrality/module.py
astrality/persistence.py
astrality/requirements.py
astrality/utils.py
astrality/xdg.py
astrality/config/astrality.yml
astrality/config/context.yml
astrality/config/modules.yml
astrality/config/modules/polybar/config.template
astrality/config/modules/polybar/init.sh
astrality/config/modules/polybar/modules.yml
astrality/config/modules/solar_desktop/afternoon.jpg
astrality/config/modules/solar_desktop/modules.yml
astrality/config/modules/solar_desktop/morning.jpg
astrality/config/modules/solar_desktop/night.jpg
astrality/config/modules/solar_desktop/performance.template
astrality/config/modules/solar_desktop/solar_colors.yml
astrality/config/modules/solar_desktop/sunrise.jpg
astrality/config/modules/solar_desktop/sunset.jpg
astrality/config/modules/solar_desktop/time.template
astrality/config/modules/terminals/alacritty.yml.template
astrality/config/modules/terminals/kitty.conf.template
astrality/tests/__init__.py
astrality/tests/conftest.py
astrality/tests/test_astrality.py
astrality/tests/test_compiler.py
astrality/tests/test_context.py
astrality/tests/test_filewatcher.py
astrality/tests/test_requirements.py
astrality/tests/test_test_utils.py
astrality/tests/test_xdg.py
astrality/tests/utils.py
astrality/tests/__pycache__/__init__.cpython-36.pyc
astrality/tests/__pycache__/conftest.cpython-36-PYTEST.pyc
astrality/tests/__pycache__/test_astrality.cpython-36-PYTEST.pyc
astrality/tests/__pycache__/test_compiler.cpython-36-PYTEST.pyc
astrality/tests/__pycache__/test_context.cpython-36-PYTEST.pyc
astrality/tests/__pycache__/test_filewatcher.cpython-36-PYTEST.pyc
astrality/tests/__pycache__/test_requirements.cpython-36-PYTEST.pyc
astrality/tests/__pycache__/test_test_utils.cpython-36-PYTEST.pyc
astrality-1.1.1.dist-info/LICENSE
astrality-1.1.1.dist-info/METADATA
astrality-1.1.1.dist-info/WHEEL
astrality-1.1.1.dist-info/top_level.txt
astrality-1.1.1.dist-info/RECORD
