Metadata-Version: 2.1
Name: astrality
Version: 1.1.1
Summary: A dynamic configuration file manager.
Home-page: http://github.com/JakobGM/astrality
Author: Jakob Gerhard Martinussen
Author-email: jakobgm@gmail.com
License: MIT
Keywords: unix configuration management
Platform: UNKNOWN
Classifier: Development Status :: 5 - Production/Stable
Classifier: Intended Audience :: End Users/Desktop
Classifier: License :: OSI Approved :: MIT License
Classifier: Natural Language :: English
Classifier: Operating System :: Unix
Classifier: Programming Language :: Python :: 3.6
Classifier: Topic :: Desktop Environment :: File Managers
Classifier: Topic :: Text Processing
Requires-Python: >=3.6
Requires-Dist: Jinja2
Requires-Dist: astral
Requires-Dist: coloredlogs
Requires-Dist: mypy-extensions
Requires-Dist: psutil
Requires-Dist: python-dateutil
Requires-Dist: pyyaml
Requires-Dist: requests
Requires-Dist: watchdog
